[
 {
  "20feet": 0,
  "20feet_quantity": "5",
  "40feet": 0,
  "40feet_quantity": "5",
  "bl_number": "897377377",
  "company_name": "MAERSK",
  "customer_name": "ABB",
  "date_du_booking": "2021-10-13",
  "docstatus": 2,
  "doctype": "Booking",
  "goods_type": "SOJA",
  "lorries": [
   {
    "parent": "897377377-ABB",
    "parentfield": "lorries",
    "parenttype": "Booking",
    "plaque": "41233BC",
    "quantit\u00e9_de_conteneur": 2
   },
   {
    "parent": "897377377-ABB",
    "parentfield": "lorries",
    "parenttype": "Booking",
    "plaque": "41233BC",
    "quantit\u00e9_de_conteneur": 44
   }
  ],
  "modified": "2021-10-06 15:29:17.115696",
  "name": "897377377-ABB",
  "parent": null,
  "parentfield": null,
  "parenttype": null,
  "price_of_dressing": 7500.0,
  "price_of_drybag": 10000.0,
  "quantity_of_bag": "20",
  "quantity_of_dressing": "5",
  "quantity_of_drybag": "10",
  "workflow_state": "Enlevement"
 },
 {
  "20feet": 0,
  "20feet_quantity": null,
  "40feet": 0,
  "40feet_quantity": null,
  "bl_number": "46545",
  "company_name": "ABL",
  "customer_name": "ABB",
  "date_du_booking": null,
  "docstatus": 0,
  "doctype": "Booking",
  "goods_type": null,
  "lorries": [],
  "modified": "2021-10-07 01:59:23.102931",
  "name": "46545-ABB",
  "parent": null,
  "parentfield": null,
  "parenttype": null,
  "price_of_dressing": 0.0,
  "price_of_drybag": 0.0,
  "quantity_of_bag": null,
  "quantity_of_dressing": null,
  "quantity_of_drybag": null,
  "workflow_state": "Facture Port"
 },
 {
  "20feet": 0,
  "20feet_quantity": null,
  "40feet": 0,
  "40feet_quantity": null,
  "bl_number": "56",
  "company_name": "MAERSK",
  "customer_name": "ABB",
  "date_du_booking": null,
  "docstatus": 2,
  "doctype": "Booking",
  "goods_type": null,
  "lorries": [],
  "modified": "2021-10-07 02:07:05.384708",
  "name": "56-ABB",
  "parent": null,
  "parentfield": null,
  "parenttype": null,
  "price_of_dressing": 0.0,
  "price_of_drybag": 0.0,
  "quantity_of_bag": null,
  "quantity_of_dressing": null,
  "quantity_of_drybag": null,
  "workflow_state": "Enlevement"
 }
]